sdg1032x/__init__.py
sdg1032x/sdg1032x.py
sdg1032x/sdg1032xminicli.py
sdg1032x_tspspi-0.0.1a1.dist-info/LICENSE.md
sdg1032x_tspspi-0.0.1a1.dist-info/METADATA
sdg1032x_tspspi-0.0.1a1.dist-info/WHEEL
sdg1032x_tspspi-0.0.1a1.dist-info/entry_points.txt
sdg1032x_tspspi-0.0.1a1.dist-info/top_level.txt
sdg1032x_tspspi-0.0.1a1.dist-info/RECORD
