Metadata-Version: 2.1
Name: sdg1032x-tspspi
Version: 0.0.1a1
Summary: Unofficial library to control SDG1032X arbitrary waveform generators
Home-page: https://github.com/tspspi/pysdg1032x
Author: Thomas Spielauer
Author-email: pypipackages01@tspi.at
License: UNKNOWN
Platform: UNKNOWN
Classifier: Programming Language :: Python :: 3
Classifier: License :: OSI Approved :: BSD License
Classifier: Operating System :: OS Independent
Requires-Python: >=3.6
License-File: LICENSE.md
